[
    {
        "name": "interets",
        "description": "Intérêts et charges assimilées.",
        "type": "number",
        "computed": false
    },
    {
        "name": "excedent_brut_d_exploitation",
        "description": "Excédent brut d'exploitation.",
        "type": "number",
        "computed": false
    },
    {
        "name": "produits_financiers",
        "description": "Produits financiers.",
        "type": "number",
        "computed": false
    },
    {
        "name": "produit_exceptionnel",
        "description": "Produits exceptionnels.",
        "type": "number",
        "computed": false
    },
    {
        "name": "charge_exceptionnelle",
        "description": "Charges exceptionnelles.",
        "type": "number",
        "computed": false
    },
    {
        "name": "charges_financieres",
        "description": "Charges financières.",
        "type": "number",
        "computed": false
    },
    {
        "name": "exercice_diane",
        "description": "Année de l'exercice",
        "type": "number",
        "computed": false
    },
    {
        "name": "arrete_bilan_diane",
        "description": "Date d'arrêté du bilan",
        "type": "string",
        "format": "date-time",
        "computed": false
    },
    {
        "name": "couverture_ca_fdr",
        "description": "Couverture du chiffre d'affaire par le fonds de roulement (exprimé en jours): Fonds de roulement net global / Chiffre d'affaires net * 360",
        "type": "number",
        "computed": false
    },
    {
        "name": "ca",
        "description": "Chiffre d'affaires",
        "type": "number",
        "computed": false
    },
    {
        "name": "concours_bancaire_courant",
        "description": "Concours bancaires courants. (Pour recalculer les frais financiers court terme de la Banque de France)",
        "type": "number",
        "computed": false
    },
    {
        "name": "valeur_ajoutee",
        "description": "Valeur ajoutée.",
        "type": "number",
        "computed": false
    },
    {
        "name": "dette_fiscale_et_sociale",
        "description": "Dette fiscale et sociale",
        "type": "number",
        "computed": false
    },
    {
        "name": "effectif_consolide",
        "description": "Effectif consolidé à l'entreprise",
        "type": "number",
        "computed": false
    },
    {
        "name": "frais_de_RetD",
        "description": "Frais de Recherche et Développement",
        "type": "number",
        "computed": false
    },
    {
        "name": "conces_brev_et_droits_sim",
        "description": "Concessions, brevets, et droits similaires",
        "type": "number",
        "computed": false
    },
    {
        "name": "nombre_etab_secondaire",
        "description": "Nombre d'établissements secondaires de l'entreprise, en plus du siège.",
        "type": "number",
        "computed": false
    },
    {
        "name": "nombre_filiale",
        "description": "Nombre de filiales de l'entreprise. Dans la base de données des liens capitalistiques, le concept de filiale ne fait aucune référence au pourcentage d’appartenance entre le parent et la fille. Dans ce sens, si l'entreprise A est enregistrée comme ayant des intérêts dans l'entreprise B avec un très petit, ou même un pourcentage de participation inconnu, l'entreprise B sera considérée filiale de l'entreprise A.",
        "type": "number",
        "computed": false
    },
    {
        "name": "taille_compo_groupe",
        "description": "Nombre d'entreprises dans le groupe (groupe défini par les liens capitalistique d'au moins 50,01%)",
        "type": "number",
        "computed": false
    },
    {
        "name": "nombre_mois",
        "description": "Durée de l'exercice en mois.",
        "type": "number",
        "computed": false
    },
    {
        "name": "equilibre_financier",
        "description": "Équilibre financier: Ressources durables / Emplois stables",
        "type": "number",
        "computed": false
    },
    {
        "name": "independance_financiere",
        "description": "Indépendance financière (exprimé en %): Fonds propres / Ressources durables * 100",
        "type": "number",
        "computed": false
    },
    {
        "name": "endettement",
        "description": "Endettement (exprimé en %): Dettes de caractère financier / Ressources durables * 100",
        "type": "number",
        "computed": false
    },
    {
        "name": "autonomie_financiere",
        "description": "Autonomie financière Fonds propres / Total bilan * 100",
        "type": "number",
        "computed": false
    },
    {
        "name": "degre_immo_corporelle",
        "description": "Degré d'amortissement des immobilisations corporelles (exprimé en %): Amortissements des immobilisations corporelles / Immobilisation corporelles brutes * 100",
        "type": "number",
        "computed": false
    },
    {
        "name": "financement_actif_circulant",
        "description": "Financement de l'actif circulant net: Fonds de roulement net global / Actif circulant net",
        "type": "number",
        "computed": false
    },
    {
        "name": "liquidite_generale",
        "description": "Liquidité générale: Actif circulant net / Dettes à court terme",
        "type": "number",
        "computed": false
    },
    {
        "name": "liquidite_reduite",
        "description": "Liquidité réduite: Actif circulant net hors stocks / Dettes à court terme",
        "type": "number",
        "computed": false
    },
    {
        "name": "rotation_stocks",
        "description": "Rotation des stocks (exprimé en jours): Stock / Chiffre d'affaires net * 360. Selon la nomenclature NAF Rév. 2 pour les secteurs d'activité 45, 46, 47, 95 (sauf 9511Z) ainsi que pour les codes d'activités 2319Z, 3831Z et 3832Z : Marchandises / (Achats de marchandises + Variation de stock) * 360",
        "type": "number",
        "computed": false
    },
    {
        "name": "credit_client",
        "description": "Crédit clients (exprimé en jours): (Clients + Effets portés à l'escompte et non échus) / Chiffre d'affaires TTC * 360",
        "type": "number",
        "computed": false
    },
    {
        "name": "credit_fournisseur",
        "description": "Crédit fournisseurs (exprimé en jours): Fournisseurs / Achats TTC * 360",
        "type": "number",
        "computed": false
    },
    {
        "name": "ca_par_effectif",
        "description": "Chiffre d'affaire par effectif (exprimé en k€/emploi): Chiffre d'affaires net / Effectif * 1000",
        "type": "number",
        "computed": false
    },
    {
        "name": "taux_interet_financier",
        "description": "Taux d'intérêt financier (exprimé en %): Intérêts / Chiffre d'affaires net * 100",
        "type": "number",
        "computed": false
    },
    {
        "name": "taux_interet_sur_ca",
        "description": "Intérêts sur chiffre d'affaire (exprimé en %): Total des charges financières / Chiffre d'affaires net * 100",
        "type": "number",
        "computed": false
    },
    {
        "name": "endettement_global",
        "description": "Endettement global (exprimé en jours): (Dettes + Effets portés à l'escompte et non échus) / Chiffre d'affaires net * 360",
        "type": "number",
        "computed": false
    },
    {
        "name": "taux_endettement",
        "description": "Taux d'endettement (exprimé en %): Dettes de caractère financier / (Capitaux propres + autres fonds propres) * 100",
        "type": "number",
        "computed": false
    },
    {
        "name": "capacite_remboursement",
        "description": "Capacité de remboursement: Dettes de caractère financier / Capacité d'autofinancement avant répartition",
        "type": "number",
        "computed": false
    },
    {
        "name": "capacite_autofinancement",
        "description": "Capacité d'autofinancement (exprimé en %): Capacité d'autofinancement avant répartition / (Chiffre d'affaires net + Subvention d'exploitation) * 100",
        "type": "number",
        "computed": false
    },
    {
        "name": "couverture_ca_besoin_fdr",
        "description": "Couverture du chiffre d'affaire par le besoin en fonds de roulement (exprimé en jours): Besoins en fonds de roulement / Chiffre d'affaires net * 360",
        "type": "number",
        "computed": false
    },
    {
        "name": "poids_bfr_exploitation",
        "description": "PoidsBFRExploitation Poids des besoins en fonds de roulement d'exploitation (exprimé en %): Besoins en fonds de roulement d'exploitation / Chiffre d'affaires net * 100",
        "type": "number",
        "computed": false
    },
    {
        "name": "exportation",
        "description": "Exportation Exportation (exprimé en %): (Chiffre d'affaires net - Chiffre d'affaires net en France) / Chiffre d'affaires net * 100",
        "type": "number",
        "computed": false
    },
    {
        "name": "efficacite_economique",
        "description": "Efficacité économique (exprimé en k€/emploi): Valeur ajoutée / Effectif * 1000",
        "type": "number",
        "computed": false
    },
    {
        "name": "productivite_potentiel_production",
        "description": "Productivité du potentiel de production: Valeur ajoutée / Immobilisations corporelles et incorporelles brutes",
        "type": "number",
        "computed": false
    },
    {
        "name": "productivite_capital_financier",
        "description": "Productivtié du capital financier: Valeur ajoutée / Actif circulant net + Effets portés à l'escompte et non échus",
        "type": "number",
        "computed": false
    },
    {
        "name": "productivite_capital_investi",
        "description": "Productivité du capital investi: Valeur ajoutée / Total de l'actif + Effets portés à l'escompte et non échus",
        "type": "number",
        "computed": false
    },
    {
        "name": "taux_d_investissement_productif",
        "description": "Taux d'investissement productif (exprimé en %): Immobilisations à valeur d'acquisition / Valeur ajoutée * 100",
        "type": "number",
        "computed": false
    },
    {
        "name": "rentabilite_economique",
        "description": "Rentabilité économique (exprimé en %): Excédent brut d'exploitation / Chiffre d'affaires net + Subventions d'exploitation * 100",
        "type": "number",
        "computed": false
    },
    {
        "name": "performance",
        "description": "Performance (exprimé en %): Résultat courant avant impôt / Chiffre d'affaires net + Subventions d'exploitation * 100",
        "type": "number",
        "computed": false
    },
    {
        "name": "rendement_brut_fonds_propres",
        "description": "Rendement brut des fonds propres (exprimé en %): Résultat courant avant impôt / Fonds propres nets * 100",
        "type": "number",
        "computed": false
    },
    {
        "name": "rentabilite_nette",
        "description": "Rentabilité nette (exprimé en %): Bénéfice ou perte / Chiffre d'affaires net + Subventions d'exploitation * 100",
        "type": "number",
        "computed": false
    },
    {
        "name": "rendement_capitaux_propres",
        "description": "Rendement des capitaux propres (exprimé en %): Bénéfice ou perte / Capitaux propres nets * 100",
        "type": "number",
        "computed": false
    },
    {
        "name": "rendement_ressources_durables",
        "description": "RendementRessourcesDurables Rendement des ressources durables (exprimé en %): Résultat courant avant impôts + Intérêts et charges assimilées / Ressources durables nettes * 100",
        "type": "number",
        "computed": false
    },
    {
        "name": "taux_marge_commerciale",
        "description": "Taux de marge commerciale (exprimé en %): Marge commerciale / Vente de marchandises * 100",
        "type": "number",
        "computed": false
    },
    {
        "name": "taux_valeur_ajoutee",
        "description": "Taux de valeur ajoutée (exprimé en %): Valeur ajoutée / Chiffre d'affaires net * 100",
        "type": "number",
        "computed": false
    },
    {
        "name": "part_salaries",
        "description": "Part des salariés (exprimé en %): (Charges de personnel + Participation des salariés aux résultats) / Valeur ajoutée * 100",
        "type": "number",
        "computed": false
    },
    {
        "name": "part_etat",
        "description": "Part de l'État (exprimé en %): Impôts et taxes / Valeur ajoutée * 100",
        "type": "number",
        "computed": false
    },
    {
        "name": "part_preteur",
        "description": "Part des prêteurs (exprimé en %): Intérêts / Valeur ajoutée * 100",
        "type": "number",
        "computed": false
    },
    {
        "name": "part_autofinancement",
        "description": "Part de l'autofinancement (exprimé en %): Capacité d'autofinancement avant répartition / Valeur ajoutée * 100",
        "type": "number",
        "computed": false
    },
    {
        "name": "ca_exportation",
        "description": "Chiffre d'affaires à l'exportation",
        "type": "number",
        "computed": false
    },
    {
        "name": "achat_marchandises",
        "description": "Achats de marchandises",
        "type": "number",
        "computed": false
    },
    {
        "name": "achat_matieres_premieres",
        "description": "Achats de matières premières et autres approvisionnement.",
        "type": "number",
        "computed": false
    },
    {
        "name": "production",
        "description": "Production de l'exercice.",
        "type": "number",
        "computed": false
    },
    {
        "name": "marge_commerciale",
        "description": "Marge commerciale.",
        "type": "number",
        "computed": false
    },
    {
        "name": "consommation",
        "description": "Consommation de l'exercice.",
        "type": "number",
        "computed": false
    },
    {
        "name": "autres_achats_charges_externes",
        "description": "Autres achats et charges externes.",
        "type": "number",
        "computed": false
    },
    {
        "name": "charge_personnel",
        "description": "Charges de personnel.",
        "type": "number",
        "computed": false
    },
    {
        "name": "impots_taxes",
        "description": "Impôts, taxes et versements assimilés.",
        "type": "number",
        "computed": false
    },
    {
        "name": "subventions_d_exploitation",
        "description": "Subventions d'exploitation.",
        "type": "number",
        "computed": false
    },
    {
        "name": "autres_produits_charges_reprises",
        "description": "Autres produits, charges et reprises.",
        "type": "number",
        "computed": false
    },
    {
        "name": "dotation_amortissement",
        "description": "Dotation d'exploitation aux amortissements et aux provisions.",
        "type": "number",
        "computed": false
    },
    {
        "name": "resultat_expl",
        "description": "Résultat d'exploitation.",
        "type": "number",
        "computed": false
    },
    {
        "name": "operations_commun",
        "description": "Opérations en commun.",
        "type": "number",
        "computed": false
    },
    {
        "name": "resultat_avant_impot",
        "description": "Résultat courant avant impôts.",
        "type": "number",
        "computed": false
    },
    {
        "name": "participation_salaries",
        "description": "Participation des salariés aux résultats.",
        "type": "number",
        "computed": false
    },
    {
        "name": "impot_benefice",
        "description": "Impôts sur les bénéfices et impôts différés.",
        "type": "number",
        "computed": false
    },
    {
        "name": "benefice_ou_perte",
        "description": "Bénéfice ou perte.",
        "type": "number",
        "computed": false
    },
    {
        "name": "interets_past_1",
        "type": "number",
        "computed": true
    },
    {
        "name": "interets_past_2",
        "type": "number",
        "computed": true
    },
    {
        "name": "excedent_brut_d_exploitation_past_1",
        "type": "number",
        "computed": true
    },
    {
        "name": "excedent_brut_d_exploitation_past_2",
        "type": "number",
        "computed": true
    },
    {
        "name": "produits_financiers_past_1",
        "type": "number",
        "computed": true
    },
    {
        "name": "produits_financiers_past_2",
        "type": "number",
        "computed": true
    },
    {
        "name": "produit_exceptionnel_past_1",
        "type": "number",
        "computed": true
    },
    {
        "name": "produit_exceptionnel_past_2",
        "type": "number",
        "computed": true
    },
    {
        "name": "charge_exceptionnelle_past_1",
        "type": "number",
        "computed": true
    },
    {
        "name": "charge_exceptionnelle_past_2",
        "type": "number",
        "computed": true
    },
    {
        "name": "charges_financieres_past_1",
        "type": "number",
        "computed": true
    },
    {
        "name": "charges_financieres_past_2",
        "type": "number",
        "computed": true
    },
    {
        "name": "exercice_diane_past_1",
        "type": "number",
        "computed": true
    },
    {
        "name": "exercice_diane_past_2",
        "type": "number",
        "computed": true
    },
    {
        "name": "arrete_bilan_diane_past_1",
        "type": "number",
        "computed": true
    },
    {
        "name": "arrete_bilan_diane_past_2",
        "type": "number",
        "computed": true
    },
    {
        "name": "couverture_ca_fdr_past_1",
        "type": "number",
        "computed": true
    },
    {
        "name": "couverture_ca_fdr_past_2",
        "type": "number",
        "computed": true
    },
    {
        "name": "ca_past_1",
        "type": "number",
        "computed": true
    },
    {
        "name": "ca_past_2",
        "type": "number",
        "computed": true
    },
    {
        "name": "concours_bancaire_courant_past_1",
        "type": "number",
        "computed": true
    },
    {
        "name": "concours_bancaire_courant_past_2",
        "type": "number",
        "computed": true
    },
    {
        "name": "valeur_ajoutee_past_1",
        "type": "number",
        "computed": true
    },
    {
        "name": "valeur_ajoutee_past_2",
        "type": "number",
        "computed": true
    },
    {
        "name": "dette_fiscale_et_sociale_past_1",
        "type": "number",
        "computed": true
    },
    {
        "name": "dette_fiscale_et_sociale_past_2",
        "type": "number",
        "computed": true
    },
    {
        "name": "effectif_consolide_past_1",
        "type": "number",
        "computed": true
    },
    {
        "name": "effectif_consolide_past_2",
        "type": "number",
        "computed": true
    },
    {
        "name": "frais_de_RetD_past_1",
        "type": "number",
        "computed": true
    },
    {
        "name": "frais_de_RetD_past_2",
        "type": "number",
        "computed": true
    },
    {
        "name": "conces_brev_et_droits_sim_past_1",
        "type": "number",
        "computed": true
    },
    {
        "name": "conces_brev_et_droits_sim_past_2",
        "type": "number",
        "computed": true
    },
    {
        "name": "nombre_etab_secondaire_past_1",
        "type": "number",
        "computed": true
    },
    {
        "name": "nombre_etab_secondaire_past_2",
        "type": "number",
        "computed": true
    },
    {
        "name": "nombre_filiale_past_1",
        "type": "number",
        "computed": true
    },
    {
        "name": "nombre_filiale_past_2",
        "type": "number",
        "computed": true
    },
    {
        "name": "taille_compo_groupe_past_1",
        "type": "number",
        "computed": true
    },
    {
        "name": "taille_compo_groupe_past_2",
        "type": "number",
        "computed": true
    },
    {
        "name": "nombre_mois_past_1",
        "type": "number",
        "computed": true
    },
    {
        "name": "nombre_mois_past_2",
        "type": "number",
        "computed": true
    },
    {
        "name": "equilibre_financier_past_1",
        "type": "number",
        "computed": true
    },
    {
        "name": "equilibre_financier_past_2",
        "type": "number",
        "computed": true
    },
    {
        "name": "independance_financiere_past_1",
        "type": "number",
        "computed": true
    },
    {
        "name": "independance_financiere_past_2",
        "type": "number",
        "computed": true
    },
    {
        "name": "endettement_past_1",
        "type": "number",
        "computed": true
    },
    {
        "name": "endettement_past_2",
        "type": "number",
        "computed": true
    },
    {
        "name": "autonomie_financiere_past_1",
        "type": "number",
        "computed": true
    },
    {
        "name": "autonomie_financiere_past_2",
        "type": "number",
        "computed": true
    },
    {
        "name": "degre_immo_corporelle_past_1",
        "type": "number",
        "computed": true
    },
    {
        "name": "degre_immo_corporelle_past_2",
        "type": "number",
        "computed": true
    },
    {
        "name": "financement_actif_circulant_past_1",
        "type": "number",
        "computed": true
    },
    {
        "name": "financement_actif_circulant_past_2",
        "type": "number",
        "computed": true
    },
    {
        "name": "liquidite_generale_past_1",
        "type": "number",
        "computed": true
    },
    {
        "name": "liquidite_generale_past_2",
        "type": "number",
        "computed": true
    },
    {
        "name": "liquidite_reduite_past_1",
        "type": "number",
        "computed": true
    },
    {
        "name": "liquidite_reduite_past_2",
        "type": "number",
        "computed": true
    },
    {
        "name": "rotation_stocks_past_1",
        "type": "number",
        "computed": true
    },
    {
        "name": "rotation_stocks_past_2",
        "type": "number",
        "computed": true
    },
    {
        "name": "credit_client_past_1",
        "type": "number",
        "computed": true
    },
    {
        "name": "credit_client_past_2",
        "type": "number",
        "computed": true
    },
    {
        "name": "credit_fournisseur_past_1",
        "type": "number",
        "computed": true
    },
    {
        "name": "credit_fournisseur_past_2",
        "type": "number",
        "computed": true
    },
    {
        "name": "ca_par_effectif_past_1",
        "type": "number",
        "computed": true
    },
    {
        "name": "ca_par_effectif_past_2",
        "type": "number",
        "computed": true
    },
    {
        "name": "taux_interet_financier_past_1",
        "type": "number",
        "computed": true
    },
    {
        "name": "taux_interet_financier_past_2",
        "type": "number",
        "computed": true
    },
    {
        "name": "taux_interet_sur_ca_past_1",
        "type": "number",
        "computed": true
    },
    {
        "name": "taux_interet_sur_ca_past_2",
        "type": "number",
        "computed": true
    },
    {
        "name": "endettement_global_past_1",
        "type": "number",
        "computed": true
    },
    {
        "name": "endettement_global_past_2",
        "type": "number",
        "computed": true
    },
    {
        "name": "taux_endettement_past_1",
        "type": "number",
        "computed": true
    },
    {
        "name": "taux_endettement_past_2",
        "type": "number",
        "computed": true
    },
    {
        "name": "capacite_remboursement_past_1",
        "type": "number",
        "computed": true
    },
    {
        "name": "capacite_remboursement_past_2",
        "type": "number",
        "computed": true
    },
    {
        "name": "capacite_autofinancement_past_1",
        "type": "number",
        "computed": true
    },
    {
        "name": "capacite_autofinancement_past_2",
        "type": "number",
        "computed": true
    },
    {
        "name": "couverture_ca_besoin_fdr_past_1",
        "type": "number",
        "computed": true
    },
    {
        "name": "couverture_ca_besoin_fdr_past_2",
        "type": "number",
        "computed": true
    },
    {
        "name": "poids_bfr_exploitation_past_1",
        "type": "number",
        "computed": true
    },
    {
        "name": "poids_bfr_exploitation_past_2",
        "type": "number",
        "computed": true
    },
    {
        "name": "exportation_past_1",
        "type": "number",
        "computed": true
    },
    {
        "name": "exportation_past_2",
        "type": "number",
        "computed": true
    },
    {
        "name": "efficacite_economique_past_1",
        "type": "number",
        "computed": true
    },
    {
        "name": "efficacite_economique_past_2",
        "type": "number",
        "computed": true
    },
    {
        "name": "productivite_potentiel_production_past_1",
        "type": "number",
        "computed": true
    },
    {
        "name": "productivite_potentiel_production_past_2",
        "type": "number",
        "computed": true
    },
    {
        "name": "productivite_capital_financier_past_1",
        "type": "number",
        "computed": true
    },
    {
        "name": "productivite_capital_financier_past_2",
        "type": "number",
        "computed": true
    },
    {
        "name": "productivite_capital_investi_past_1",
        "type": "number",
        "computed": true
    },
    {
        "name": "productivite_capital_investi_past_2",
        "type": "number",
        "computed": true
    },
    {
        "name": "taux_d_investissement_productif_past_1",
        "type": "number",
        "computed": true
    },
    {
        "name": "taux_d_investissement_productif_past_2",
        "type": "number",
        "computed": true
    },
    {
        "name": "rentabilite_economique_past_1",
        "type": "number",
        "computed": true
    },
    {
        "name": "rentabilite_economique_past_2",
        "type": "number",
        "computed": true
    },
    {
        "name": "performance_past_1",
        "type": "number",
        "computed": true
    },
    {
        "name": "performance_past_2",
        "type": "number",
        "computed": true
    },
    {
        "name": "rendement_brut_fonds_propres_past_1",
        "type": "number",
        "computed": true
    },
    {
        "name": "rendement_brut_fonds_propres_past_2",
        "type": "number",
        "computed": true
    },
    {
        "name": "rentabilite_nette_past_1",
        "type": "number",
        "computed": true
    },
    {
        "name": "rentabilite_nette_past_2",
        "type": "number",
        "computed": true
    },
    {
        "name": "rendement_capitaux_propres_past_1",
        "type": "number",
        "computed": true
    },
    {
        "name": "rendement_capitaux_propres_past_2",
        "type": "number",
        "computed": true
    },
    {
        "name": "rendement_ressources_durables_past_1",
        "type": "number",
        "computed": true
    },
    {
        "name": "rendement_ressources_durables_past_2",
        "type": "number",
        "computed": true
    },
    {
        "name": "taux_marge_commerciale_past_1",
        "type": "number",
        "computed": true
    },
    {
        "name": "taux_marge_commerciale_past_2",
        "type": "number",
        "computed": true
    },
    {
        "name": "taux_valeur_ajoutee_past_1",
        "type": "number",
        "computed": true
    },
    {
        "name": "taux_valeur_ajoutee_past_2",
        "type": "number",
        "computed": true
    },
    {
        "name": "part_salaries_past_1",
        "type": "number",
        "computed": true
    },
    {
        "name": "part_salaries_past_2",
        "type": "number",
        "computed": true
    },
    {
        "name": "part_etat_past_1",
        "type": "number",
        "computed": true
    },
    {
        "name": "part_etat_past_2",
        "type": "number",
        "computed": true
    },
    {
        "name": "part_preteur_past_1",
        "type": "number",
        "computed": true
    },
    {
        "name": "part_preteur_past_2",
        "type": "number",
        "computed": true
    },
    {
        "name": "part_autofinancement_past_1",
        "type": "number",
        "computed": true
    },
    {
        "name": "part_autofinancement_past_2",
        "type": "number",
        "computed": true
    },
    {
        "name": "ca_exportation_past_1",
        "type": "number",
        "computed": true
    },
    {
        "name": "ca_exportation_past_2",
        "type": "number",
        "computed": true
    },
    {
        "name": "achat_marchandises_past_1",
        "type": "number",
        "computed": true
    },
    {
        "name": "achat_marchandises_past_2",
        "type": "number",
        "computed": true
    },
    {
        "name": "achat_matieres_premieres_past_1",
        "type": "number",
        "computed": true
    },
    {
        "name": "achat_matieres_premieres_past_2",
        "type": "number",
        "computed": true
    },
    {
        "name": "production_past_1",
        "type": "number",
        "computed": true
    },
    {
        "name": "production_past_2",
        "type": "number",
        "computed": true
    },
    {
        "name": "marge_commerciale_past_1",
        "type": "number",
        "computed": true
    },
    {
        "name": "marge_commerciale_past_2",
        "type": "number",
        "computed": true
    },
    {
        "name": "consommation_past_1",
        "type": "number",
        "computed": true
    },
    {
        "name": "consommation_past_2",
        "type": "number",
        "computed": true
    },
    {
        "name": "autres_achats_charges_externes_past_1",
        "type": "number",
        "computed": true
    },
    {
        "name": "autres_achats_charges_externes_past_2",
        "type": "number",
        "computed": true
    },
    {
        "name": "charge_personnel_past_1",
        "type": "number",
        "computed": true
    },
    {
        "name": "charge_personnel_past_2",
        "type": "number",
        "computed": true
    },
    {
        "name": "impots_taxes_past_1",
        "type": "number",
        "computed": true
    },
    {
        "name": "impots_taxes_past_2",
        "type": "number",
        "computed": true
    },
    {
        "name": "subventions_d_exploitation_past_1",
        "type": "number",
        "computed": true
    },
    {
        "name": "subventions_d_exploitation_past_2",
        "type": "number",
        "computed": true
    },
    {
        "name": "autres_produits_charges_reprises_past_1",
        "type": "number",
        "computed": true
    },
    {
        "name": "autres_produits_charges_reprises_past_2",
        "type": "number",
        "computed": true
    },
    {
        "name": "dotation_amortissement_past_1",
        "type": "number",
        "computed": true
    },
    {
        "name": "dotation_amortissement_past_2",
        "type": "number",
        "computed": true
    },
    {
        "name": "resultat_expl_past_1",
        "type": "number",
        "computed": true
    },
    {
        "name": "resultat_expl_past_2",
        "type": "number",
        "computed": true
    },
    {
        "name": "operations_commun_past_1",
        "type": "number",
        "computed": true
    },
    {
        "name": "operations_commun_past_2",
        "type": "number",
        "computed": true
    },
    {
        "name": "resultat_avant_impot_past_1",
        "type": "number",
        "computed": true
    },
    {
        "name": "resultat_avant_impot_past_2",
        "type": "number",
        "computed": true
    },
    {
        "name": "participation_salaries_past_1",
        "type": "number",
        "computed": true
    },
    {
        "name": "participation_salaries_past_2",
        "type": "number",
        "computed": true
    },
    {
        "name": "impot_benefice_past_1",
        "type": "number",
        "computed": true
    },
    {
        "name": "impot_benefice_past_2",
        "type": "number",
        "computed": true
    },
    {
        "name": "benefice_ou_perte_past_1",
        "type": "number",
        "computed": true
    },
    {
        "name": "benefice_ou_perte_past_2",
        "type": "number",
        "computed": true
    },
    {
        "name": "poids_frng",
        "type": "number",
        "computed": true
    },
    {
        "name": "taux_marge",
        "type": "number",
        "computed": true
    },
    {
        "name": "dette_fiscale",
        "type": "number",
        "computed": true
    },
    {
        "name": "financier_court_terme",
        "type": "number",
        "computed": true
    },
    {
        "name": "frais_financier",
        "type": "number",
        "computed": true
    },
    {
        "name": "poids_frng_past_1",
        "type": "number",
        "computed": true
    },
    {
        "name": "poids_frng_past_2",
        "type": "number",
        "computed": true
    },
    {
        "name": "taux_marge_past_1",
        "type": "number",
        "computed": true
    },
    {
        "name": "taux_marge_past_2",
        "type": "number",
        "computed": true
    },
    {
        "name": "dette_fiscale_past_1",
        "type": "number",
        "computed": true
    },
    {
        "name": "dette_fiscale_past_2",
        "type": "number",
        "computed": true
    },
    {
        "name": "financier_court_terme_past_1",
        "type": "number",
        "computed": true
    },
    {
        "name": "financier_court_terme_past_2",
        "type": "number",
        "computed": true
    },
    {
        "name": "frais_financier_past_1",
        "type": "number",
        "computed": true
    },
    {
        "name": "frais_financier_past_2",
        "type": "number",
        "computed": true
    }
]
